LICENSE.md
MANIFEST.in
README.md
pyspeedtest.py
setup.py
pyspeedtest.egg-info/PKG-INFO
pyspeedtest.egg-info/SOURCES.txt
pyspeedtest.egg-info/dependency_links.txt
pyspeedtest.egg-info/entry_points.txt
pyspeedtest.egg-info/top_level.txt