Metadata-Version: 1.1
Name: pyspeedtest
Version: 1.2.2
Summary: Speedtest.net Python script
Home-page: https://github.com/fopina/pyspeedtest
Author: Filipe Pina
Author-email: fopina@skmobi.com
License: MIT
Download-URL: https://github.com/fopina/pyspeedtest/tarball/v1.2.2
Keywords: speedtest.net,speedtest,speed,test,bandwidth
Platform: UNKNOWN
Classifier: Development Status :: 4 - Beta
Classifier: Intended Audience :: Developers
Classifier: License :: OSI Approved :: MIT License
Classifier: Operating System :: OS Independent
Classifier: Programming Language :: Python
Classifier: Programming Language :: Python
Classifier: Programming Language :: Python :: 2
Classifier: Programming Language :: Python :: 2.7
Classifier: Programming Language :: Python :: 3
Classifier: Programming Language :: Python :: 3.0
Classifier: Programming Language :: Python :: 3.1
Classifier: Programming Language :: Python :: 3.2
Classifier: Programming Language :: Python :: 3.3
Classifier: Programming Language :: Python :: 3.4
Classifier: Programming Language :: Python :: 3.5
